arexecute/__init__.py
arexecute/__main__.py
arexecute/core/__init__.py
arexecute/core/actions.py
arexecute/core/arkey.py
arexecute/core/core_utils.py
arexecute/core/filehandler.py
arexecute/core/recorder_executer.py
arexecute/core/executer/__init__.py
arexecute/core/executer/executer.py
arexecute/core/recorder/__init__.py
arexecute/core/recorder/recorder.py
arexecute/core/recorder/state.py
arexecute/json_creator/__init__.py
arexecute/json_creator/json_directions.py
arexecute/keyutils/__init__.py
arexecute/keyutils/keypresswrapper.py
arexecute/keyutils/keyset.py
arexecute-1.0.2.dist-info/LICENSE
arexecute-1.0.2.dist-info/METADATA
arexecute-1.0.2.dist-info/WHEEL
arexecute-1.0.2.dist-info/entry_points.txt
arexecute-1.0.2.dist-info/top_level.txt
arexecute-1.0.2.dist-info/RECORD
