Metadata-Version: 2.1
Name: arexecute
Version: 1.0.2
Summary: Record and execute actions
Home-page: https://github.com/jurrutiag/arexecute
Author: Juan Urrutia
Author-email: juan.urrutia.gandolfo@gmail.com
License: MIT
Platform: UNKNOWN
Classifier: License :: OSI Approved :: MIT License
Classifier: Programming Language :: Python
Classifier: Programming Language :: Python :: 3
Classifier: Programming Language :: Python :: 3.6
Classifier: Programming Language :: Python :: 3.7
Classifier: Programming Language :: Python :: 3.8
Requires-Dist: pynput (>=1.7.1)
Requires-Dist: pyautogui (>=0.9.50)
